sachi/__init__.py
sachi/__main__.py
sachi/app.py
sachi/app.tcss
sachi/cli.py
sachi/config.py
sachi/context.py
sachi/models.py
sachi/resources/__init__.py
sachi/resources/config.toml
sachi/screens/__init__.py
sachi/screens/episodes.py
sachi/screens/episodes.tcss
sachi/screens/rename.py
sachi/screens/rename.tcss
sachi/sources/__init__.py
sachi/sources/base.py
sachi/sources/custom.py
sachi/sources/tvdb.py
sachi-0.4.0.dist-info/METADATA
sachi-0.4.0.dist-info/WHEEL
sachi-0.4.0.dist-info/entry_points.txt
sachi-0.4.0.dist-info/licenses/LICENSE
sachi-0.4.0.dist-info/RECORD
