Metadata-Version: 2.4
Name: sachi
Version: 0.4.0
Summary: Terminal media files renamer (FileBot alternative)
Project-URL: homepage, https://github.com/NextFire/sachi
Author-email: NextFire <git@yuru.moe>
License-Expression: MIT
License-File: LICENSE
Requires-Python: >=3.12
Requires-Dist: aiohttp[speedups]==3.11.11
Requires-Dist: backoff==2.2.1
Requires-Dist: guessit==3.8.0
Requires-Dist: jinja2==3.1.4
Requires-Dist: pydantic==2.10.4
Requires-Dist: pymediainfo==6.1.0
Requires-Dist: setuptools==75.6.0
Requires-Dist: textual==1.0.0
Requires-Dist: tomlkit==0.13.2
Requires-Dist: typer==0.15.1
Requires-Dist: yarl==1.18.3
